[
  {
    "id": "29045842",
    "img": "",
    "ext": "",
    "now": "2020-08-02(日)14:20:44",
    "userid": "ZWgmXKA",
    "name": "无名氏",
    "email": "",
    "title": "无标题",
    "content": "<font color=\"#789922\">&gt;&gt;No.29045772</font><br />\n阿陆那边，我本来想着如果也是大铁那个模式，得先努努力满足条件才能实现愿望的话，还可以打断这一过程来阻止愿望实现。<br />\n但身体改造类的，多半是建国那样，大金天自己就能完成了…",
    "sage": "0",
    "admin": "0",
    "status": "n"
  },
  {
    "id": "29046273",
    "img": "",
    "ext": "",
    "now": "2020-08-02(日)14:40:43",
    "userid": "52FIpZi",
    "name": "无名氏",
    "email": "",
    "title": "无标题",
    "content": "2去会会他(　ﾟ 3ﾟ)",
    "sage": "0",
    "admin": "0",
    "status": "n"
  },
  {
    "id": "29046507",
    "img": "",
    "ext": "",
    "now": "2020-08-02(日)14:51:21",
    "userid": "52FIpZi",
    "name": "无名氏",
    "email": "",
    "title": "无标题",
    "content": "我觉得陆生那边属于一个倒计时，我们要在陆生彻底凉了之前把大金天解决掉",
    "sage": "0",
    "admin": "0",
    "status": "n"
  },
  {
    "id": "29046637",
    "img": "",
    "ext": "",
    "now": "2020-08-02(日)14:56:26",
    "userid": "ZWgmXKA",
    "name": "无名氏",
    "email": "",
    "title": "无标题",
    "content": "<font color=\"#789922\">&gt;&gt;No.29045540</font><br />\n补一下，男生三人被看到也就算了，主要让学姐藏好一点，暗中确认",
    "sage": "0",
    "admin": "0",
    "status": "n"
  },
  {
    "id": "29047416",
    "img": "",
    "ext": "",
    "now": "2020-08-02(日)15:30:03",
    "userid": "fxc8mDE",
    "name": "无名氏",
    "email": "",
    "title": "无标题",
    "content": "<font color=\"#789922\">&gt;&gt;No.29046637</font><br />\n基本上都是2，剧情将按着2发展ﾟ ∀ﾟ)ノ",
    "sage": "0",
    "admin": "0",
    "status": "n"
  },
  {
    "id": "29047452",
    "img": "",
    "ext": "",
    "now": "2020-08-02(日)15:31:40",
    "userid": "fxc8mDE",
    "name": "无名氏",
    "email": "",
    "title": "无标题",
    "content": "<font color=\"#789922\">&gt;&gt;No.29047416</font><br />\n<br />\n「我们马上就去。」<br />\r\n你给老大回复到。<br />\r\n“我们先去教室吧，在门口看看里面什么情况再说。”说完你又把两条士力架分别给了磊子和学姐，你渐渐放慢脚步走到队尾的学姐身边说：“学姐，你看阿陆的状态……他？”<br />\r\n学姐将士力架放进包中说：“愿力发作，什么时候死只是时间问题。只是不知道「祂」将怎么实现陆生的愿望？无法确定陆生最终会像陈建国那样还是像大铁一样。”<br />\r\n你暗自握紧了拳头，希望「周教授」那能有新的线索。<br />\r\n…<br />\r\n……<br />\r\n你、陆生还有磊子三人鬼鬼祟祟的站在教室门口朝里面望去。<br />\r\n教室内人头攒动，怎么也得有个将近200人。「周筑玉」教授正在讲台上调试设备，他好像还没注意到门口的你们。<br />\r\n突然叮铃铃——的上课铃声在你们头上炸响，吓得你们三人一嘚瑟赶紧缩头到门后。<br />\r\n「周筑玉」教授将麦别在衣领上清了清嗓子说：<br />\r\n“门外的三名同学进来吧，开始上课了。”<br />\r\n周学姐快速在本子上写到：<br />\r\n「样貌、声音都跟我兄长不一样。」<br />\n\r<br />\n你决定_____<br />\n\r<br />\n1.你们三人进去上课<br />\r\n2.喊着学姐一起，四人进去上课<br />\r\n3.不进去上课，在门外等教授上完课尾随他<br />\r\n4.不进去上课，离开这里",
    "sage": "0",
    "admin": "0",
    "status": "n"
  },
  {
    "id": "29047483",
    "img": "",
    "ext": "",
    "now": "2020-08-02(日)15:32:48",
    "userid": "52FIpZi",
    "name": "无名氏",
    "email": "",
    "title": "无标题",
    "content": "2(　ﾟ 3ﾟ)",
    "sage": "0",
    "admin": "0",
    "status": "n"
  },
  {
    "id": "29047933",
    "img": "",
    "ext": "",
    "now": "2020-08-02(日)15:51:02",
    "userid": "CtO8jRn",
    "name": "无名氏",
    "email": "",
    "title": "无标题",
    "content": "是敌是友？<br />\n<br />\n假如是友，那么兄长应当是用了某种手段改变了自己的样貌，目的是骗过大金天，此时带着学姐去上课，应该会让他能在课上或者课间提供一些信息<br />\n<br />\n假如是敌，那么真正的兄长应该还在别的地方，不上课去四处寻找真人，等下课再尾随教授才是正解<br />\n<br />\n我觉得应该问一下学姐，兄长会不会易容伪装之类的手段<br />\n<br />\n兄长身上也有不能改变的特点，那就是和学姐一样的鲜红舌头，也可以尝试从这里入手，看看这个周教授是真是假",
    "sage": "0",
    "admin": "0",
    "status": "n"
  },
  {
    "id": "29048088",
    "img": "",
    "ext": "",
    "now": "2020-08-02(日)15:56:40",
    "userid": "fxc8mDE",
    "name": "无名氏",
    "email": "",
    "title": "无标题",
    "content": "<font color=\"#789922\">&gt;&gt;No.29047933</font><br />\n<br />\n“学姐，你兄长会易容术啊伪装术啊这些的吗？”你悄声问着学姐，学姐在本子上写到：「当然不会。」<br />\r\n“呃，你们刚谁注意到了教授的嘴巴有没有什么异常之处？”<br />\r\n“真没注意到，而且这离的太远了，也看不清啊……”磊子无奈的回答到，陆生也点了点头表示同意。<br />\n\r<br />\n你决定_____<br />\n\r<br />\n1.你们三人进去上课<br />\r\n2.喊着学姐一起，四人进去上课<br />\r\n3.不进去上课，在门外等教授上完课尾随他<br />\r\n4.不进去上课，离开这里",
    "sage": "0",
    "admin": "0",
    "status": "n"
  },
  {
    "id": "29049210",
    "img": "",
    "ext": "",
    "now": "2020-08-02(日)16:43:03",
    "userid": "ZWgmXKA",
    "name": "无名氏",
    "email": "",
    "title": "无标题",
    "content": "2，先问问学姐她觉得自己要不要进，要的话就遮上点脸坐磊子后面吧( ﾟдﾟ)<br />\n课间的时候找教授问问题，顺便看看舌头",
    "sage": "0",
    "admin": "0",
    "status": "n"
  },
  {
    "id": "29049288",
    "img": "",
    "ext": "",
    "now": "2020-08-02(日)16:46:09",
    "userid": "ZWgmXKA",
    "name": "无名氏",
    "email": "",
    "title": "无标题",
    "content": "<font color=\"#789922\">&gt;&gt;No.29049210</font><br />\n也让学姐再试试联系一下大舅子吧，不然如果这个教授有假，也没线索找真哥了",
    "sage": "0",
    "admin": "0",
    "status": "n"
  },
  {
    "id": "29049331",
    "img": "",
    "ext": "",
    "now": "2020-08-02(日)16:47:32",
    "userid": "tisKmgW",
    "name": "无名氏",
    "email": "",
    "title": "无标题",
    "content": "<font color=\"#789922\">&gt;&gt;No.29049210</font><br />\n附议",
    "sage": "0",
    "admin": "0",
    "status": "n"
  },
  {
    "id": "29050001",
    "img": "",
    "ext": "",
    "now": "2020-08-02(日)17:13:03",
    "userid": "fxc8mDE",
    "name": "无名氏",
    "email": "",
    "title": "无标题",
    "content": "<font color=\"#789922\">&gt;&gt;No.29049331</font><br />\n<font color=\"#789922\">&gt;&gt;No.29049288</font><br />\n<font color=\"#789922\">&gt;&gt;No.29049210</font><br />\n<br />\n“学姐，你能再试试联系下你兄长吗？”<br />\r\n周学姐拨通了她兄长的电话，你听到了一个机械的女声说到：「您所拨打的电话不在服务区，请稍后再试。sorry，the number you ——」<br />\r\n你扶着额头，内心来回挣扎。<br />\n你真的难以决断到底要不要进去，又问到学姐：“学姐，你觉得我们应该进去吗？”<br />\r\n学姐耸耸肩说：“我个人觉得不要进去，这位「周筑玉」教授绝对不是我兄长「周筑玉」。你们要不要进去，全凭你们自己的判断。”<br />\n\r<br />\n你决定_____<br />\n\r<br />\n1.你们三人进去上课<br />\r\n2.不进去上课，在门外等教授上完课尾随他<br />\r\n3.不进去上课，离开这里",
    "sage": "0",
    "admin": "0",
    "status": "n"
  },
  {
    "id": "29050249",
    "img": "",
    "ext": "",
    "now": "2020-08-02(日)17:22:10",
    "userid": "YJcZ5F3",
    "name": "无名氏",
    "email": "",
    "title": "无标题",
    "content": "这时候和学姐分开不太好，还是23里选<br />\n<br />\n学姐如此肯定这人不是兄长，然而真正的兄长还活着，这就意味着兄长在另外的地方<br />\n<br />\n尾随这人可能会被这人带入圈套，而且会浪费等待下课的这段时间<br />\n<br />\n所以还是先离开，看看别的地方能不能有所发现，等大课下课前15分钟再来尾随假货好了",
    "sage": "0",
    "admin": "0",
    "status": "n"
  },
  {
    "id": "29050468",
    "img": "",
    "ext": "",
    "now": "2020-08-02(日)17:31:15",
    "userid": "zYQguww",
    "name": "无名氏",
    "email": "",
    "title": "无标题",
    "content": "1，教室人这么多，就算他是假的也不能拿我们怎么样，观察教授后没啥问题的话还可以休息会。学姐一个人应该也不会去哪里吧|∀` )",
    "sage": "0",
    "admin": "0",
    "status": "n"
  },
  {
    "id": "29050622",
    "img": "",
    "ext": "",
    "now": "2020-08-02(日)17:36:51",
    "userid": "ZWgmXKA",
    "name": "无名氏",
    "email": "",
    "title": "无标题",
    "content": "2，但是只留磊子进去上课，尽量把关键内容记纸上<br />\n我陆生学姐三人在教室外面先讨论讨论，看下一步怎么走，找真兄还是怎么着。<br />\n我不信popo设计最后这么一个人物一点用没有，最好还是调查调查 ",
    "sage": "0",
    "admin": "0",
    "status": "n"
  },
  {
    "id": "29050711",
    "img": "",
    "ext": "",
    "now": "2020-08-02(日)17:40:38",
    "userid": "tisKmgW",
    "name": "无名氏",
    "email": "",
    "title": "无标题",
    "content": "有没有学姐因某种原因判断错误这种可能呢(・∀・)",
    "sage": "0",
    "admin": "0",
    "status": "n"
  },
  {
    "id": "29050951",
    "img": "",
    "ext": "",
    "now": "2020-08-02(日)17:49:35",
    "userid": "ZWgmXKA",
    "name": "无名氏",
    "email": "",
    "title": "无标题",
    "content": "<font color=\"#789922\">&gt;&gt;No.29050711</font><br />\n有可能，毕竟大金天幻象几乎全覆盖，学姐一个人还没法回san。<br />\n具体可以翻翻前面几位肥哥分析的学姐疑点 ",
    "sage": "0",
    "admin": "0",
    "status": "n"
  },
  {
    "id": "29051901",
    "img": "",
    "ext": "",
    "now": "2020-08-02(日)18:24:06",
    "userid": "e7buiOO",
    "name": "无名氏",
    "email": "",
    "title": "无标题",
    "content": "卡99了( ・_ゝ・)",
    "sage": "0",
    "admin": "0",
    "status": "n"
  }
]
