[
  {
    "id": "29115928",
    "img": "",
    "ext": "",
    "now": "2020-08-04(二)19:30:53",
    "userid": "DejC1TS",
    "name": "无名氏",
    "email": "",
    "title": "无标题",
    "content": "<font color=\"#789922\">&gt;&gt;No.29115706</font><br />\n这个也行σ`∀´)附议",
    "sage": "0",
    "admin": "0",
    "status": "n"
  },
  {
    "id": "29115971",
    "img": "",
    "ext": "",
    "now": "2020-08-04(二)19:32:05",
    "userid": "aowf7Iu",
    "name": "无名氏",
    "email": "",
    "title": "无标题",
    "content": "(｀･ω･)有没有什么好主意骗他让他能说实验有点危险，让他反锁寝室？晚上寝室里的人肯定会变怪砸门感觉<br />\n没有好主意的话3赶走或者5打晕也可以吧，( ﾟ∀。)我都想5直接把他打晕丢下去杀了，但是估计会出更大的问题。。。。<br />\n<br />\n暂时选3",
    "sage": "0",
    "admin": "0",
    "status": "n"
  },
  {
    "id": "29116015",
    "img": "",
    "ext": "",
    "now": "2020-08-04(二)19:33:16",
    "userid": "ZWgmXKA",
    "name": "无名氏",
    "email": "",
    "title": "无标题",
    "content": "<font color=\"#789922\">&gt;&gt;No.29115971</font><br />\n “兄啊，我听广播说纵火犯很可能是学校里的人，晚上睡觉锁门吧( ´_ゝ`)”",
    "sage": "0",
    "admin": "0",
    "status": "n"
  },
  {
    "id": "29116056",
    "img": "",
    "ext": "",
    "now": "2020-08-04(二)19:34:40",
    "userid": "ZWgmXKA",
    "name": "无名氏",
    "email": "",
    "title": "无标题",
    "content": "刚想起来，我们把老三扣下来，宿舍剩下俩人会不会上来找他(|||ﾟДﾟ)我们要来一个绑一个吗",
    "sage": "0",
    "admin": "0",
    "status": "n"
  },
  {
    "id": "29116064",
    "img": "",
    "ext": "",
    "now": "2020-08-04(二)19:34:55",
    "userid": "FToovvr",
    "name": "无名氏",
    "email": "",
    "title": "无标题",
    "content": "npc狂暴化的触发器很可能是“不合理行为”<br />\n <br />\n5很明显，太不合理了；<br />\n而3的话，老三发现被耍，带着老大上来找我们，我们不开门，也很不合理。",
    "sage": "0",
    "admin": "0",
    "status": "n"
  },
  {
    "id": "29116093",
    "img": "",
    "ext": "",
    "now": "2020-08-04(二)19:36:15",
    "userid": "FToovvr",
    "name": "无名氏",
    "email": "",
    "title": "无标题",
    "content": "<font color=\"#789922\">&gt;&gt;No.29116064</font><br />\n( ﾟ∀。)反而套套能合理化一切",
    "sage": "0",
    "admin": "0",
    "status": "n"
  },
  {
    "id": "29116157",
    "img": "",
    "ext": "",
    "now": "2020-08-04(二)19:38:44",
    "userid": "CtO8jRn",
    "name": "无名氏",
    "email": "",
    "title": "无标题",
    "content": "假称实验，让老三下去把这些没买的东西买给我们是否可行？<br />\n杀虫喷雾的理由是虫子多要杀虫<br />\n酒精和玻璃瓶则是实验需要的用品",
    "sage": "0",
    "admin": "0",
    "status": "n"
  },
  {
    "id": "29116183",
    "img": "",
    "ext": "",
    "now": "2020-08-04(二)19:39:59",
    "userid": "ZWgmXKA",
    "name": "无名氏",
    "email": "",
    "title": "无标题",
    "content": "<font color=\"#789922\">&gt;&gt;No.29116093</font><br />\npc风评被害･ﾟ( ﾉヮ´ )真·给佬成了",
    "sage": "0",
    "admin": "0",
    "status": "n"
  },
  {
    "id": "29116273",
    "img": "",
    "ext": "",
    "now": "2020-08-04(二)19:43:30",
    "userid": "ZWgmXKA",
    "name": "无名氏",
    "email": "",
    "title": "无标题",
    "content": "<font color=\"#789922\">&gt;&gt;No.29116157</font><br />\n附议",
    "sage": "0",
    "admin": "0",
    "status": "n"
  },
  {
    "id": "29116343",
    "img": "",
    "ext": "",
    "now": "2020-08-04(二)19:45:29",
    "userid": "FToovvr",
    "name": "无名氏",
    "email": "",
    "title": "无标题",
    "content": "<font color=\"#789922\">&gt;&gt;No.29116157</font><br />\n<br />\n我才想起来，酒精是从实验室偷出来的吧，我们只能让老三带正常途径能获取的东西吧",
    "sage": "0",
    "admin": "0",
    "status": "n"
  },
  {
    "id": "29116478",
    "img": "",
    "ext": "",
    "now": "2020-08-04(二)19:50:09",
    "userid": "ZWgmXKA",
    "name": "无名氏",
    "email": "",
    "title": "无标题",
    "content": "<font color=\"#789922\">&gt;&gt;No.29116343</font><br />\n超市买两瓶二锅头也可以呀",
    "sage": "0",
    "admin": "0",
    "status": "n"
  },
  {
    "id": "29116486",
    "img": "",
    "ext": "",
    "now": "2020-08-04(二)19:50:14",
    "userid": "CtO8jRn",
    "name": "无名氏",
    "email": "",
    "title": "无标题",
    "content": "<font color=\"#789922\">&gt;&gt;No.29116343</font><br />\n那就把酒精换成二锅头，就说我们大晚上做实验需要二锅头来提神醒脑（好假）",
    "sage": "0",
    "admin": "0",
    "status": "n"
  },
  {
    "id": "29116560",
    "img": "",
    "ext": "",
    "now": "2020-08-04(二)19:52:45",
    "userid": "d8uAv5d",
    "name": "无名氏",
    "email": "",
    "title": "无标题",
    "content": "酒精是溶剂，可以洗颜料或者胶水什么的",
    "sage": "0",
    "admin": "0",
    "status": "n"
  },
  {
    "id": "29116566",
    "img": "",
    "ext": "",
    "now": "2020-08-04(二)19:52:59",
    "userid": "FToovvr",
    "name": "无名氏",
    "email": "",
    "title": "无标题",
    "content": "<font color=\"#789922\">&gt;&gt;No.29116486</font> <br />\n搜了下，好像可以点燃，那应该可行吧(ゝ∀･)",
    "sage": "0",
    "admin": "0",
    "status": "n"
  },
  {
    "id": "29116591",
    "img": "",
    "ext": "",
    "now": "2020-08-04(二)19:53:46",
    "userid": "CtO8jRn",
    "name": "无名氏",
    "email": "",
    "title": "无标题",
    "content": "<font color=\"#789922\">&gt;&gt;No.29116566</font><br />\n之前网吧那里用的就是二锅头",
    "sage": "0",
    "admin": "0",
    "status": "n"
  },
  {
    "id": "29116632",
    "img": "",
    "ext": "",
    "now": "2020-08-04(二)19:55:03",
    "userid": "ZWgmXKA",
    "name": "无名氏",
    "email": "",
    "title": "无标题",
    "content": "颜料也易燃，可能还更好找<br />\n当然有酒精最好还是酒精 ",
    "sage": "0",
    "admin": "0",
    "status": "n"
  },
  {
    "id": "29116713",
    "img": "",
    "ext": "",
    "now": "2020-08-04(二)19:58:16",
    "userid": "FToovvr",
    "name": "无名氏",
    "email": "",
    "title": "无标题",
    "content": "<font color=\"#789922\">&gt;&gt;No.29116591</font><br />\n翻了翻原文，二进鬼屋那里有二锅头，而且po说可以用纱布组成燃烧瓶。那应该没问题<br />\n<br />\n<br />\n<font color=\"#789922\">&gt;&gt;No.28840616</font>",
    "sage": "0",
    "admin": "0",
    "status": "n"
  },
  {
    "id": "29116819",
    "img": "",
    "ext": "",
    "now": "2020-08-04(二)20:01:55",
    "userid": "ZWgmXKA",
    "name": "无名氏",
    "email": "",
    "title": "无标题",
    "content": "<font color=\"#789922\">&gt;&gt;No.29116713</font><br />\nnice！如果决定让老三帮忙买回来的话，加上套套也可以哦(〃∀〃)",
    "sage": "0",
    "admin": "0",
    "status": "n"
  },
  {
    "id": "29116844",
    "img": "",
    "ext": "",
    "now": "2020-08-04(二)20:02:49",
    "userid": "FToovvr",
    "name": "无名氏",
    "email": "",
    "title": "无标题",
    "content": "多让老三带点二锅头和啤酒，然后给老三支付宝转200说不要把这件事说出去，让老三认为这是我们“其实是要在天台过夜喝酒”的封口费",
    "sage": "0",
    "admin": "0",
    "status": "n"
  }
]
