[
  {
    "id": "33453004",
    "img": "",
    "ext": "",
    "now": "2020-12-31(四)20:41:21",
    "userid": "qoqDx7F",
    "name": "无名氏",
    "email": "",
    "title": "无标题",
    "content": "<font color=\"#789922\">&gt;&gt;No.33452429</font><br />\n我也感觉还不会出现( ﾟ∀。)<br />\n不过起码前面已经出现“弟弟”线索，俺准备遇到就直接“我的……好弟弟？还是说……好哥哥？”( ﾟ∀。)",
    "sage": "0",
    "admin": "0",
    "status": "n"
  },
  {
    "id": "33453058",
    "img": "",
    "ext": "",
    "now": "2020-12-31(四)20:43:05",
    "userid": "wdselU6",
    "name": "无名氏",
    "email": "",
    "title": "无标题",
    "content": "2",
    "sage": "0",
    "admin": "0",
    "status": "n"
  },
  {
    "id": "33453277",
    "img": "",
    "ext": "",
    "now": "2020-12-31(四)20:51:33",
    "userid": "pNUJfnZ",
    "name": "无名氏",
    "email": "",
    "title": "无标题",
    "content": "2",
    "sage": "0",
    "admin": "0",
    "status": "n"
  },
  {
    "id": "33453296",
    "img": "",
    "ext": "",
    "now": "2020-12-31(四)20:52:23",
    "userid": "pNUJfnZ",
    "name": "无名氏",
    "email": "",
    "title": "无标题",
    "content": "<font color=\"#789922\">&gt;&gt;No.33453004</font><br />\npc视角看应该是我的好弟弟吧( ﾟ∀ﾟ)",
    "sage": "0",
    "admin": "0",
    "status": "n"
  },
  {
    "id": "33453582",
    "img": "",
    "ext": "",
    "now": "2020-12-31(四)21:03:15",
    "userid": "Ec6tzay",
    "name": "无名氏",
    "email": "",
    "title": "无标题",
    "content": "先放个蹲po在这( ﾟ∀。)",
    "sage": "0",
    "admin": "0",
    "status": "n"
  },
  {
    "id": "33454241",
    "img": "",
    "ext": "",
    "now": "2020-12-31(四)21:28:52",
    "userid": "qoqDx7F",
    "name": "无名氏",
    "email": "",
    "title": "无标题",
    "content": "蹲popo( ﾟ∀ﾟ)",
    "sage": "0",
    "admin": "0",
    "status": "n"
  },
  {
    "id": "33454622",
    "img": "",
    "ext": "",
    "now": "2020-12-31(四)21:41:50",
    "userid": "fxc8mDE",
    "name": "无名氏",
    "email": "",
    "title": "无标题",
    "content": "2选项得票最多，剧情将按着这个发展ﾟ ∀ﾟ)ノ",
    "sage": "0",
    "admin": "0",
    "status": "n"
  },
  {
    "id": "33454636",
    "img": "",
    "ext": "",
    "now": "2020-12-31(四)21:42:47",
    "userid": "fxc8mDE",
    "name": "无名氏",
    "email": "",
    "title": "无标题",
    "content": "<font color=\"#789922\">&gt;&gt;No.33454622</font><br />\n<br />\n你留在聚光灯下保持警惕。<br />\n正如黎明临近，黑影逃遁。<br />\n仅剩你们二人的世界中，床上的他沉溺于甜蜜的梦乡。你们像隔着一层朦胧的毛玻璃，奇怪的是——<br />\n虽然看不清脸，但你知道那就是他。<br />\n一个你不应该忘却也不能忘却的人。<br />\n可是当你想要追忆亦或是联想，属于他的所有又在你脑海中被尽数抹去。就像蓝色依旧是蓝色，只是失去了自由的含义。<br />\n一切归于没有情绪的灰色。<br />\n「他是谁？」<br />\n没有答案的问题如影随形般根植进脑海，你知道如果你无法解答，他将存在于你每个惊醒汗湿的夜晚。<br />\n“醒醒。”<br />\n你大汗淋漓的被万越唤醒，他递给你一瓶矿泉水:<br />\n“你又做噩梦了。”<br />\n“难受我可以替你请假。”<br />\n你看向手机，已经临近3点。<br />\n<br />\n你_____<br />\n<br />\n1.不请，参加活动<br />\n2.请假，留在山庄",
    "sage": "0",
    "admin": "0",
    "status": "n"
  },
  {
    "id": "33454674",
    "img": "",
    "ext": "",
    "now": "2020-12-31(四)21:44:16",
    "userid": "qoqDx7F",
    "name": "无名氏",
    "email": "",
    "title": "无标题",
    "content": "时间管理大师不能说不行( ﾟ∀。)9",
    "sage": "0",
    "admin": "0",
    "status": "n"
  },
  {
    "id": "33454706",
    "img": "",
    "ext": "",
    "now": "2020-12-31(四)21:45:20",
    "userid": "Ec6tzay",
    "name": "无名氏",
    "email": "",
    "title": "无标题",
    "content": "1<br />\n啊这个颜色的指代又出现了",
    "sage": "0",
    "admin": "0",
    "status": "n"
  },
  {
    "id": "33454726",
    "img": "",
    "ext": "",
    "now": "2020-12-31(四)21:46:14",
    "userid": "qoqDx7F",
    "name": "无名氏",
    "email": "",
    "title": "无标题",
    "content": "选个1( ﾟ∀。)",
    "sage": "0",
    "admin": "0",
    "status": "n"
  },
  {
    "id": "33454730",
    "img": "",
    "ext": "",
    "now": "2020-12-31(四)21:46:31",
    "userid": "qoqDx7F",
    "name": "无名氏",
    "email": "",
    "title": "无标题",
    "content": "<font color=\"#789922\">&gt;&gt;No.33454706</font><br />\n是诶，上次就乱猜没什么头绪( ﾟ∀。)",
    "sage": "0",
    "admin": "0",
    "status": "n"
  },
  {
    "id": "33454798",
    "img": "",
    "ext": "",
    "now": "2020-12-31(四)21:48:45",
    "userid": "Ec6tzay",
    "name": "无名氏",
    "email": "",
    "title": "无标题",
    "content": "<font color=\"#789922\">&gt;&gt;No.33454730</font><br />\n我之前是觉得暂时不必过度引申，明确引用的也就只有指代pc的蓝色而已",
    "sage": "0",
    "admin": "0",
    "status": "n"
  },
  {
    "id": "33454823",
    "img": "",
    "ext": "",
    "now": "2020-12-31(四)21:49:30",
    "userid": "5lpSqH7",
    "name": "无名氏",
    "email": "",
    "title": "无标题",
    "content": "1",
    "sage": "0",
    "admin": "0",
    "status": "n"
  },
  {
    "id": "33455217",
    "img": "",
    "ext": "",
    "now": "2020-12-31(四)22:01:37",
    "userid": "Ec6tzay",
    "name": "无名氏",
    "email": "",
    "title": "无标题",
    "content": "从第0天晚上起pc每次睡觉都会做不太好的梦( ﾟ∀。)",
    "sage": "0",
    "admin": "0",
    "status": "n"
  },
  {
    "id": "33455278",
    "img": "",
    "ext": "",
    "now": "2020-12-31(四)22:04:06",
    "userid": "qoqDx7F",
    "name": "无名氏",
    "email": "",
    "title": "无标题",
    "content": "<font color=\"#789922\">&gt;&gt;No.33455217</font><br />\n确实( ﾟ∀。)",
    "sage": "0",
    "admin": "0",
    "status": "n"
  },
  {
    "id": "33455476",
    "img": "",
    "ext": "",
    "now": "2020-12-31(四)22:10:35",
    "userid": "pNUJfnZ",
    "name": "无名氏",
    "email": "",
    "title": "无标题",
    "content": "好哥哥･ﾟ( ﾉд`ﾟ)",
    "sage": "0",
    "admin": "0",
    "status": "n"
  },
  {
    "id": "33455481",
    "img": "",
    "ext": "",
    "now": "2020-12-31(四)22:10:50",
    "userid": "pNUJfnZ",
    "name": "无名氏",
    "email": "",
    "title": "无标题",
    "content": "1冲进寒潭( `д´)",
    "sage": "0",
    "admin": "0",
    "status": "n"
  },
  {
    "id": "33455531",
    "img": "",
    "ext": "",
    "now": "2020-12-31(四)22:12:15",
    "userid": "pNUJfnZ",
    "name": "无名氏",
    "email": "",
    "title": "无标题",
    "content": "<font color=\"#789922\">&gt;&gt;No.33455217</font><br />\npc被误入猛鬼街无误( ﾟ∀。)",
    "sage": "0",
    "admin": "0",
    "status": "n"
  }
]