[
  {
    "id": "29872775",
    "img": "",
    "ext": "",
    "now": "2020-08-28(五)19:52:14",
    "userid": "r2g2ljq",
    "name": "无名氏",
    "email": "",
    "title": "无标题",
    "content": "五连就算了 还要都是0(`ε´ )不知道这个概率多少啊( `д´)σ",
    "sage": "0",
    "admin": "0",
    "status": "n"
  },
  {
    "id": "29872888",
    "img": "",
    "ext": "",
    "now": "2020-08-28(五)19:55:28",
    "userid": "2mt0KiS",
    "name": "无名氏",
    "email": "",
    "title": "无标题",
    "content": "<font color=\"#789922\">&gt;&gt;No.29872634</font><br />\n逊啦ﾟ ∀ﾟ)ノ",
    "sage": "0",
    "admin": "0",
    "status": "n"
  },
  {
    "id": "29872890",
    "img": "",
    "ext": "",
    "now": "2020-08-28(五)19:55:34",
    "userid": "sz1ltaz",
    "name": "无名氏",
    "email": "",
    "title": "无标题",
    "content": "<font color=\"#789922\">&gt;&gt;No.29872696</font><br />\n小鸟是异常冷静地让我们出去吧...",
    "sage": "0",
    "admin": "0",
    "status": "n"
  },
  {
    "id": "29872905",
    "img": "",
    "ext": "",
    "now": "2020-08-28(五)19:55:59",
    "userid": "gkrq7Zz",
    "name": "无名氏",
    "email": "",
    "title": "无标题",
    "content": "<font color=\"#789922\">&gt;&gt;No.29872634</font><br />\n这个po就是玩不起啦(σﾟ∀ﾟ)σ",
    "sage": "0",
    "admin": "0",
    "status": "n"
  },
  {
    "id": "29872912",
    "img": "",
    "ext": "",
    "now": "2020-08-28(五)19:56:14",
    "userid": "sz1ltaz",
    "name": "无名氏",
    "email": "",
    "title": "无标题",
    "content": "抱歉看错了，我紫菜",
    "sage": "0",
    "admin": "0",
    "status": "n"
  },
  {
    "id": "29872941",
    "img": "",
    "ext": "",
    "now": "2020-08-28(五)19:57:02",
    "userid": "r2g2ljq",
    "name": "无名氏",
    "email": "",
    "title": "无标题",
    "content": "选3的肥哥要考虑到<br />\n我们现在疑似进入单对单恶意梦境里（虽然不知道这小鸟是咋回事） 发出声音并不一定能传达到正常世界位面(=ﾟωﾟ)= 即使传达出去了 也不一定就有用了 更不知道的是发声会有什么事情<br />\n<br />\n这样的话 突然有些担心女生房间了 <br />\n万一那个房间里触发对单恶意的正好是翁语涵呢( ・_ゝ・) ",
    "sage": "0",
    "admin": "0",
    "status": "n"
  },
  {
    "id": "29872955",
    "img": "",
    "ext": "",
    "now": "2020-08-28(五)19:57:38",
    "userid": "sz1ltaz",
    "name": "无名氏",
    "email": "",
    "title": "无标题",
    "content": "也可能是黑泥怪通过小鸟的异常反逼我们出去？参考怪谈2中仿生人表现出的智力，也不是不可能。",
    "sage": "0",
    "admin": "0",
    "status": "n"
  },
  {
    "id": "29872983",
    "img": "",
    "ext": "",
    "now": "2020-08-28(五)19:58:28",
    "userid": "VTrxICm",
    "name": "无名氏",
    "email": "",
    "title": "无标题",
    "content": "<font color=\"#789922\">&gt;&gt;No.29872955</font><br />\n那这就形成永无止境的猜疑链啦(つд⊂)",
    "sage": "0",
    "admin": "0",
    "status": "n"
  },
  {
    "id": "29872999",
    "img": "",
    "ext": "",
    "now": "2020-08-28(五)19:59:07",
    "userid": "lDxT7In",
    "name": "无名氏",
    "email": "",
    "title": "无标题",
    "content": "小鸟不简单啊，不愧是和婉约哥和温婉并列的重要角色(`ヮ´ )<br />\n我觉得小鸟作为重要角色的特殊性如果只体现在“八字弱”的话也太弱了，肯定还有别的方面的，不管这里小鸟是“ooc”“另一个人格”“被附身”还是“本性暴露，之前全是演戏”，小鸟的重要性都体现出来了<br />\n我倾向小鸟是帮我们的，问就是直觉，没有依据(`ヮ´ )<br />\n附加老吴之前的说法：<br />\n【老吴的目光飘向远处的叶袅接着说：<br />\n“准确的说，是老板夫妻最可疑。叶袅我不能确定，但他看起来不像是装的，除非他演技真的出神入化。”】",
    "sage": "0",
    "admin": "0",
    "status": "n"
  },
  {
    "id": "29873037",
    "img": "",
    "ext": "",
    "now": "2020-08-28(五)20:00:20",
    "userid": "r2g2ljq",
    "name": "无名氏",
    "email": "",
    "title": "无标题",
    "content": "<font color=\"#789922\">&gt;&gt;No.29872955</font><br />\n没有叶袅拉住 pc已经是在极度恐慌的情况下 没有大脑考虑地「条件反射地想要逃出门外」啦( ﾟωﾟ) <br />\n根本不用他动手哦 ",
    "sage": "0",
    "admin": "0",
    "status": "n"
  },
  {
    "id": "29873132",
    "img": "",
    "ext": "",
    "now": "2020-08-28(五)20:03:41",
    "userid": "sz1ltaz",
    "name": "无名氏",
    "email": "",
    "title": "无标题",
    "content": "“仿生人”可能是黑泥化形成的...并且这里的叶袅也表现出“仿生人”的情感淡漠，我猜测“喷涌而出的黑泥”化形成了叶袅？（这里po没检查旁边的叶袅吧...并且叶袅只可能是在我醒来之前起床，但那样又和“翻回叶袅那边”矛盾。",
    "sage": "0",
    "admin": "0",
    "status": "n"
  },
  {
    "id": "29873156",
    "img": "",
    "ext": "",
    "now": "2020-08-28(五)20:04:34",
    "userid": "sz1ltaz",
    "name": "无名氏",
    "email": "",
    "title": "无标题",
    "content": "<font color=\"#789922\">&gt;&gt;No.29873132</font><br />\n抱歉，没理顺就发出来了。<br />\n“仿生人”可能是黑泥化形成的...并且这里的叶袅也表现出“仿生人”的情感淡漠，我猜测“喷涌而出的黑泥”化形成了叶袅？（这里po没检查旁边的叶袅吧...并且叶袅只可能是在我醒来之前起床，否则就和“翻回叶袅那边”矛盾。",
    "sage": "0",
    "admin": "0",
    "status": "n"
  },
  {
    "id": "29873160",
    "img": "",
    "ext": "",
    "now": "2020-08-28(五)20:04:40",
    "userid": "r2g2ljq",
    "name": "无名氏",
    "email": "",
    "title": "无标题",
    "content": "其实我已经在往<br />\n小鸟通灵体质易被附身 <br />\n然后我们这群人中正好有可以附身他人进入梦境的通灵者角度考虑了(`ヮ´ )",
    "sage": "0",
    "admin": "0",
    "status": "n"
  },
  {
    "id": "29873164",
    "img": "",
    "ext": "",
    "now": "2020-08-28(五)20:04:46",
    "userid": "2mt0KiS",
    "name": "无名氏",
    "email": "",
    "title": "无标题",
    "content": "<font color=\"#789922\">&gt;&gt;No.29872999</font><br />\n太细了肥哥( ´∀`)",
    "sage": "0",
    "admin": "0",
    "status": "n"
  },
  {
    "id": "29873253",
    "img": "",
    "ext": "",
    "now": "2020-08-28(五)20:07:58",
    "userid": "r2g2ljq",
    "name": "无名氏",
    "email": "",
    "title": "无标题",
    "content": "“叶袅”不正常是肯定的<br />\n可是从哪看出来情感淡漠像仿生人呢( ﾟωﾟ)只有一句话和一个眼神呀 我觉得这个推测并不充分 只有到下一回合才能更见分晓",
    "sage": "0",
    "admin": "0",
    "status": "n"
  },
  {
    "id": "29873289",
    "img": "",
    "ext": "",
    "now": "2020-08-28(五)20:09:10",
    "userid": "r2g2ljq",
    "name": "无名氏",
    "email": "",
    "title": "无标题",
    "content": "<font color=\"#789922\">&gt;&gt;No.29873156</font><br />\n如果是这样的话 你觉得应该选什么好一点",
    "sage": "0",
    "admin": "0",
    "status": "n"
  },
  {
    "id": "29873332",
    "img": "",
    "ext": "",
    "now": "2020-08-28(五)20:10:30",
    "userid": "sz1ltaz",
    "name": "无名氏",
    "email": "",
    "title": "无标题",
    "content": "<font color=\"#789922\">&gt;&gt;No.29873289</font><br />\n叫万越？",
    "sage": "0",
    "admin": "0",
    "status": "n"
  },
  {
    "id": "29873352",
    "img": "",
    "ext": "",
    "now": "2020-08-28(五)20:10:53",
    "userid": "gkrq7Zz",
    "name": "无名氏",
    "email": "",
    "title": "无标题",
    "content": "2不变应万变|∀` )",
    "sage": "0",
    "admin": "0",
    "status": "n"
  },
  {
    "id": "29873517",
    "img": "",
    "ext": "",
    "now": "2020-08-28(五)20:16:47",
    "userid": "G7U1s1t",
    "name": "无名氏",
    "email": "",
    "title": "无标题",
    "content": "<font color=\"#789922\">&gt;&gt;No.29869173</font><br />\n当时可能是出现了一个可靠人物保护了pcﾟ ∀ﾟ)ノ<br />\n<br />\n怪谈里的黑泥怪并没有表现出物理攻击，可能是精神污染之类的吧。说不定黑泥怪就是想要把pc骗出去？存疑。<br />\n<font color=\"#789922\">&gt;&gt;No.29873156</font><br />\n小鸟在之前是背对着pc睡的，突然翻身用被子盖住也有可能。<br />\n<br />\n婉约的话不至于听不到猫叫吧(;´Д`)但是婉约睡姿那么放松听不到猫叫也有可能…",
    "sage": "0",
    "admin": "0",
    "status": "n"
  }
]