[
  {
    "id": "30491544",
    "img": "",
    "ext": "",
    "now": "2020-09-18(五)21:35:07",
    "userid": "FgYQCRo",
    "name": "无名氏",
    "email": "",
    "title": "无标题",
    "content": "为啥今天的讨论话题感觉都像结团了似的( ﾟ∀。)不管是人物塑造，还是起名字，还是结团奖励",
    "sage": "0",
    "admin": "0",
    "status": "n"
  },
  {
    "id": "30491614",
    "img": "",
    "ext": "",
    "now": "2020-09-18(五)21:37:31",
    "userid": "qoqDx7F",
    "name": "无名氏",
    "email": "",
    "title": "无标题",
    "content": "<font color=\"#789922\">&gt;&gt;No.30491544</font><br />\n懂了( ﾟ∀。)今天是结团（前）一个月纪念日或者（前）一周年纪念日⊂彡☆))∀`)",
    "sage": "0",
    "admin": "0",
    "status": "n"
  },
  {
    "id": "30491615",
    "img": "",
    "ext": "",
    "now": "2020-09-18(五)21:37:37",
    "userid": "o72A6wF",
    "name": "无名氏",
    "email": "",
    "title": "无标题",
    "content": "<font color=\"#789922\">&gt;&gt;No.30491544</font><br />\n( ﾟ∀。)结果六百多页才第二天",
    "sage": "0",
    "admin": "0",
    "status": "n"
  },
  {
    "id": "30491634",
    "img": "",
    "ext": "",
    "now": "2020-09-18(五)21:38:04",
    "userid": "o72A6wF",
    "name": "无名氏",
    "email": "",
    "title": "无标题",
    "content": "･ﾟ( ﾉヮ´ )这团感觉这能变成季节团",
    "sage": "0",
    "admin": "0",
    "status": "n"
  },
  {
    "id": "30491635",
    "img": "",
    "ext": "",
    "now": "2020-09-18(五)21:38:06",
    "userid": "fxc8mDE",
    "name": "无名氏",
    "email": "",
    "title": "无标题",
    "content": "3选项得票最多，以及附议最多的加入剧情，剧情将按着这个发展ﾟ ∀ﾟ)ノ",
    "sage": "0",
    "admin": "0",
    "status": "n"
  },
  {
    "id": "30491692",
    "img": "",
    "ext": "",
    "now": "2020-09-18(五)21:40:30",
    "userid": "qoqDx7F",
    "name": "无名氏",
    "email": "",
    "title": "无标题",
    "content": "<font color=\"#789922\">&gt;&gt;No.29556631</font><br />\n今天是开团一个月纪念日倒是真的(ゝ∀･)",
    "sage": "0",
    "admin": "0",
    "status": "n"
  },
  {
    "id": "30491736",
    "img": "",
    "ext": "",
    "now": "2020-09-18(五)21:41:56",
    "userid": "fxc8mDE",
    "name": "无名氏",
    "email": "",
    "title": "无标题",
    "content": "<font color=\"#789922\">&gt;&gt;No.30491635</font><br />\n<br />\n“这一路来太艰险了，「推门」肯定有更多风险，让我忍不住打退堂鼓……可是我又想要「推门」回去救你……现在的心情非常矛盾，我不知道该怎么选了。”你犹犹豫豫的跟「叶袅」咬起耳朵。<br />\r\n“你救不了我。”「叶袅」不假思索的接着说：“你认识到了风险，这点很好。我个人希望你，不要「推门」。”<br />\n“事实就是「门内」比这里更加危险，百闻不如一见，我可以带你——也只有「我」可以带你坐电梯去到「门内」最外围见识见识，其中利害你自然明了。”<br />\r\n「叶袅」皱着眉头感觉自己说得太过直白而显得十分功利，他叹了口气缓缓解释道：<br />\r\n“我知道你对我的感情……可能是因为忘记或者…记不全，并不如你现在身边所珍视的同伴们。你或许并不相信我，但你为了叶袅的身体考虑也得信一信我。”<br />\r\n“我能出现在「叶袅」身上除了八字外他体质根基最差、生气也最弱。这样的他很容易被我这种「脏东西」附身。”<br />\r\n“其实从你们靠近寒潭后我就已经附在他身上了，从那之后你们的一举一动我都可以通过他的眼睛看见。我无意伤害他，更无意夺舍他的意识。只有等他完全沉睡后我再出来才能最大限度上减少对他身体的负担，他体质本来就差，又流了这么多血。小肠上的伤口…扩大也是时间和行动决定的。往后拖没有及时的医疗保障，极有可能会引起腹膜炎甚至脓毒血症。到时候，就真的救不了了。”<br />\r\n“我不知道你知不知道，姑且算是不知道吧。我相信没有「门内」记忆的韩沐也无法告诉你太多，「门内」的时间是「逆时间」，叶袅呆在那里可以缓解他伤口的恶化程度。但是，「祂」即将沉睡，「门」也会随之消失。你不要侥幸的把「推门」当做最后的补救机会，「门」不会一直在那里，「它」随时都会关闭。所以，你如果跟我一起乘坐电梯下去，你必须在「门」彻底关闭前将叶袅接出来，否则他会被永远留在里面。由于「我」身处「门内」，我预测「门」最晚在明天中午就会关闭。所以，你必须在明天中午前将叶袅接出。”<br />\r\n“当然，一切的前提是你相信我的话，并且愿意跟我搭乘电梯。”<br />\r\n“不要说「我再想想」，时间来不及了，我可以在路上跟你具体说明……你愿意吗？”<br />\n\r<br />\n你_____<br />\n\r<br />\n1.愿意<br />\r\n2.不愿意",
    "sage": "0",
    "admin": "0",
    "status": "n"
  },
  {
    "id": "30491771",
    "img": "",
    "ext": "",
    "now": "2020-09-18(五)21:43:16",
    "userid": "fxc8mDE",
    "name": "无名氏",
    "email": "",
    "title": "无标题",
    "content": "<font color=\"#789922\">&gt;&gt;No.30490920</font><br />\n<br />\n理论上来说可以活，但鱼和熊掌不可兼得ﾟ ∀ﾟ)ノ",
    "sage": "0",
    "admin": "0",
    "status": "n"
  },
  {
    "id": "30491787",
    "img": "",
    "ext": "",
    "now": "2020-09-18(五)21:43:46",
    "userid": "o72A6wF",
    "name": "无名氏",
    "email": "",
    "title": "无标题",
    "content": "<font color=\"#789922\">&gt;&gt;No.30491771</font><br />\nﾟ ∀ﾟ)ノ 大师 我悟了",
    "sage": "0",
    "admin": "0",
    "status": "n"
  },
  {
    "id": "30491812",
    "img": "",
    "ext": "",
    "now": "2020-09-18(五)21:44:58",
    "userid": "FgYQCRo",
    "name": "无名氏",
    "email": "",
    "title": "无标题",
    "content": "1先走再说，既然时间紧迫<br />\n<br />\n最坏情况万一代打哥是个狗币，那就pc自尽拯救地球",
    "sage": "0",
    "admin": "0",
    "status": "n"
  },
  {
    "id": "30491819",
    "img": "",
    "ext": "",
    "now": "2020-09-18(五)21:45:04",
    "userid": "o72A6wF",
    "name": "无名氏",
    "email": "",
    "title": "无标题",
    "content": "愿意吧( ´ー`)<br />\n但是要问一下把鸟接出来的办法",
    "sage": "0",
    "admin": "0",
    "status": "n"
  },
  {
    "id": "30491842",
    "img": "",
    "ext": "",
    "now": "2020-09-18(五)21:45:42",
    "userid": "r2g2ljq",
    "name": "无名氏",
    "email": "",
    "title": "无标题",
    "content": "<font color=\"#789922\">&gt;&gt;No.30491771</font><br />\n啊( ﾟ∀。)<br />\n<br />\n看来除非打出理论全活结局 不然全活很难了( ・_ゝ・) ",
    "sage": "0",
    "admin": "0",
    "status": "n"
  },
  {
    "id": "30491862",
    "img": "",
    "ext": "",
    "now": "2020-09-18(五)21:46:23",
    "userid": "qoqDx7F",
    "name": "无名氏",
    "email": "",
    "title": "无标题",
    "content": "我悟了<br />\n诺兰直呼内行(*ﾟ∇ﾟ)",
    "sage": "0",
    "admin": "0",
    "status": "n"
  },
  {
    "id": "30491874",
    "img": "",
    "ext": "",
    "now": "2020-09-18(五)21:46:41",
    "userid": "FgYQCRo",
    "name": "无名氏",
    "email": "",
    "title": "无标题",
    "content": "1但温婉怎么办。。",
    "sage": "0",
    "admin": "0",
    "status": "n"
  },
  {
    "id": "30491878",
    "img": "",
    "ext": "",
    "now": "2020-09-18(五)21:46:52",
    "userid": "r2g2ljq",
    "name": "无名氏",
    "email": "",
    "title": "无标题",
    "content": "………原来阴间电梯真的是阴间的入口( ﾟдﾟ)",
    "sage": "0",
    "admin": "0",
    "status": "n"
  },
  {
    "id": "30491882",
    "img": "",
    "ext": "",
    "now": "2020-09-18(五)21:47:00",
    "userid": "o72A6wF",
    "name": "无名氏",
    "email": "",
    "title": "无标题",
    "content": "<font color=\"#789922\">&gt;&gt;No.30491842</font><br />\n( ´_ゝ`)最坏就是即使全活也会因为顾全这个丢了那个之类重伤残疾精神失常吧<br />\n算了 走一步看一步",
    "sage": "0",
    "admin": "0",
    "status": "n"
  },
  {
    "id": "30491892",
    "img": "",
    "ext": "",
    "now": "2020-09-18(五)21:47:32",
    "userid": "o72A6wF",
    "name": "无名氏",
    "email": "",
    "title": "无标题",
    "content": "<font color=\"#789922\">&gt;&gt;No.30491874</font><br />\n是啊( ﾟ∀ﾟ)怎么办呢 也问问代打哥吧",
    "sage": "0",
    "admin": "0",
    "status": "n"
  },
  {
    "id": "30491905",
    "img": "",
    "ext": "",
    "now": "2020-09-18(五)21:47:56",
    "userid": "r2g2ljq",
    "name": "无名氏",
    "email": "",
    "title": "无标题",
    "content": "对啊温婉怎么办( ﾟдﾟ)<br />\n问问代打哥？有没有什么暂时绝对安全的地方？温婉可以让她先去夹层里藏起来吗 ",
    "sage": "0",
    "admin": "0",
    "status": "n"
  },
  {
    "id": "30491912",
    "img": "",
    "ext": "",
    "now": "2020-09-18(五)21:48:07",
    "userid": "qoqDx7F",
    "name": "无名氏",
    "email": "",
    "title": "无标题",
    "content": "1附议问下温婉咋办",
    "sage": "0",
    "admin": "0",
    "status": "n"
  }
]