[
  {
    "id": "30719051",
    "img": "",
    "ext": "",
    "now": "2020-09-26(六)21:37:51",
    "userid": "qoqDx7F",
    "name": "无名氏",
    "email": "",
    "title": "无标题",
    "content": "温——老——板——（？）<br />\n还不知道是不是屑人呢( ・_ゝ・)",
    "sage": "0",
    "admin": "0",
    "status": "n"
  },
  {
    "id": "30719111",
    "img": "",
    "ext": "",
    "now": "2020-09-26(六)21:39:52",
    "userid": "r2g2ljq",
    "name": "无名氏",
    "email": "",
    "title": "无标题",
    "content": "下来还会收获温婉线线索是我没想到的",
    "sage": "0",
    "admin": "0",
    "status": "n"
  },
  {
    "id": "30719132",
    "img": "",
    "ext": "",
    "now": "2020-09-26(六)21:40:26",
    "userid": "r2g2ljq",
    "name": "无名氏",
    "email": "",
    "title": "无标题",
    "content": "<font color=\"#789922\">&gt;&gt;No.30718938</font><br />\n<font color=\"#789922\">&gt;&gt;No.30718963</font><br />\nfxc的岛刚刚炸了没･ﾟ( ﾉヮ´ )",
    "sage": "0",
    "admin": "0",
    "status": "n"
  },
  {
    "id": "30719415",
    "img": "",
    "ext": "",
    "now": "2020-09-26(六)21:50:56",
    "userid": "o72A6wF",
    "name": "无名氏",
    "email": "",
    "title": "无标题",
    "content": "还真要回去问问温婉你爸死了没( ﾟ∀。)<br />\n这么一看温婉她爹大概率也经历过推门……",
    "sage": "0",
    "admin": "0",
    "status": "n"
  },
  {
    "id": "30719467",
    "img": "",
    "ext": "",
    "now": "2020-09-26(六)21:52:49",
    "userid": "OedwoD8",
    "name": "无名氏",
    "email": "",
    "title": "无标题",
    "content": "先问代打哥我们能不能捡垃圾出去",
    "sage": "0",
    "admin": "0",
    "status": "n"
  },
  {
    "id": "30719497",
    "img": "",
    "ext": "",
    "now": "2020-09-26(六)21:53:56",
    "userid": "h1uKxl2",
    "name": "无名氏",
    "email": "",
    "title": "无标题",
    "content": "捡垃圾可还行，也太莽了吧( ﾟ∀。)",
    "sage": "0",
    "admin": "0",
    "status": "n"
  },
  {
    "id": "30719530",
    "img": "",
    "ext": "",
    "now": "2020-09-26(六)21:54:39",
    "userid": "OedwoD8",
    "name": "无名氏",
    "email": "",
    "title": "无标题",
    "content": "<font color=\"#789922\">&gt;&gt;No.30719415</font><br />\n记住尸体穿的西装的牌子，然后上去和温婉说：你爸的xx牌西装真靓仔(　^ω^)（混沌假想，非正式补充内容）",
    "sage": "0",
    "admin": "0",
    "status": "n"
  },
  {
    "id": "30719555",
    "img": "",
    "ext": "",
    "now": "2020-09-26(六)21:55:18",
    "userid": "OedwoD8",
    "name": "无名氏",
    "email": "",
    "title": "无标题",
    "content": "<font color=\"#789922\">&gt;&gt;No.30719497</font><br />\n或者说问代打哥，我们触碰这些尸体会不会有什么变故( ﾟ∀。)",
    "sage": "0",
    "admin": "0",
    "status": "n"
  },
  {
    "id": "30719651",
    "img": "",
    "ext": "",
    "now": "2020-09-26(六)21:57:52",
    "userid": "fxc8mDE",
    "name": "无名氏",
    "email": "",
    "title": "无标题",
    "content": "<font color=\"#789922\">&gt;&gt;No.30719132</font><br />\n<br />\n炸了  更新间隔10分钟( ﾟ∀。)<br />\n刚想发  发现发不了( ﾟ∀。)",
    "sage": "0",
    "admin": "0",
    "status": "n"
  },
  {
    "id": "30719675",
    "img": "",
    "ext": "",
    "now": "2020-09-26(六)21:58:36",
    "userid": "OedwoD8",
    "name": "无名氏",
    "email": "",
    "title": "无标题",
    "content": "难怪刚才那段讨论的人这么少|∀` )",
    "sage": "0",
    "admin": "0",
    "status": "n"
  },
  {
    "id": "30719795",
    "img": "",
    "ext": "",
    "now": "2020-09-26(六)22:02:14",
    "userid": "r2g2ljq",
    "name": "无名氏",
    "email": "",
    "title": "无标题",
    "content": "<font color=\"#789922\">&gt;&gt;No.30719651</font><br />\n都卡得刷不出来･ﾟ( ﾉヮ´ )",
    "sage": "0",
    "admin": "0",
    "status": "n"
  },
  {
    "id": "30720232",
    "img": "",
    "ext": "",
    "now": "2020-09-26(六)22:15:21",
    "userid": "qoqDx7F",
    "name": "无名氏",
    "email": "",
    "title": "无标题",
    "content": "<font color=\"#789922\">&gt;&gt;No.30719415</font><br />\n温婉说不定会冲下来看呢( ´ー`)如果她爹也是神秘失踪状态的话( ・_ゝ・)",
    "sage": "0",
    "admin": "0",
    "status": "n"
  },
  {
    "id": "30720265",
    "img": "",
    "ext": "",
    "now": "2020-09-26(六)22:16:47",
    "userid": "F2bH7dH",
    "name": "无名氏",
    "email": "",
    "title": "无标题",
    "content": "可以问代打，垃圾场中是否有死亡风险，死在垃圾场的人对于外界来说会是什么样。<br />\n<br />\n如果ok安全，可以考虑由韩沐挨个把其他人都接下来避难，留婉约和pc在外面寻找解法。老吴也算了，他再有行动力也只不过是个普通上班族中年肥肥还是苟住老命要紧",
    "sage": "0",
    "admin": "0",
    "status": "n"
  },
  {
    "id": "30720336",
    "img": "",
    "ext": "",
    "now": "2020-09-26(六)22:18:56",
    "userid": "qoqDx7F",
    "name": "无名氏",
    "email": "",
    "title": "无标题",
    "content": "如果温婉她爹也推门了，难道会回到酒店刚开业的时候？纯瞎猜( ´_ゝ`)",
    "sage": "0",
    "admin": "0",
    "status": "n"
  },
  {
    "id": "30720507",
    "img": "",
    "ext": "",
    "now": "2020-09-26(六)22:24:19",
    "userid": "r2g2ljq",
    "name": "无名氏",
    "email": "",
    "title": "无标题",
    "content": "<font color=\"#789922\">&gt;&gt;No.30720232</font><br />\n没有其他门内人她下不来的",
    "sage": "0",
    "admin": "0",
    "status": "n"
  },
  {
    "id": "30720523",
    "img": "",
    "ext": "",
    "now": "2020-09-26(六)22:24:50",
    "userid": "h1uKxl2",
    "name": "无名氏",
    "email": "",
    "title": "无标题",
    "content": "温婉她爹也不知道是作为过去推门人存在的，还是处于我们的轮回中被我们害死的( ﾟ∀。)",
    "sage": "0",
    "admin": "0",
    "status": "n"
  },
  {
    "id": "30720527",
    "img": "",
    "ext": "",
    "now": "2020-09-26(六)22:24:58",
    "userid": "F2bH7dH",
    "name": "无名氏",
    "email": "",
    "title": "无标题",
    "content": "如果黑社会是推门人，推门人又有可能是杀老板的人",
    "sage": "0",
    "admin": "0",
    "status": "n"
  },
  {
    "id": "30720599",
    "img": "",
    "ext": "",
    "now": "2020-09-26(六)22:27:00",
    "userid": "r2g2ljq",
    "name": "无名氏",
    "email": "",
    "title": "无标题",
    "content": "<font color=\"#789922\">&gt;&gt;No.30720265</font><br />\n一个个运输中途风险太大 耗时长且麻烦<br />\n而且太被动了 这可不是什么好地方 应该想着怎么出去而不是在这里避难<br />\n并且上下条件苛刻 如果找到突破口怎么快速把这么多人带过去转移？万一正好门内人不在呢？ ",
    "sage": "0",
    "admin": "0",
    "status": "n"
  },
  {
    "id": "30720658",
    "img": "",
    "ext": "",
    "now": "2020-09-26(六)22:28:46",
    "userid": "r2g2ljq",
    "name": "无名氏",
    "email": "",
    "title": "无标题",
    "content": "而且代打说了不能让老板知道这里 对于其他人也没法好好解释<br />\n没有老板我们也下不来 老板在这他这么虚弱出了事情也没法镇场 其他人又都是普通人 ",
    "sage": "0",
    "admin": "0",
    "status": "n"
  }
]