[
  {
    "id": "30726671",
    "img": "",
    "ext": "",
    "now": "2020-09-27(日)03:08:10",
    "userid": "qoqDx7F",
    "name": "无名氏",
    "email": "",
    "title": "无标题",
    "content": "<font color=\"#789922\">&gt;&gt;No.30726612</font><br />\n弱智了，应该引用的(;´Д`)影响观感非常抱歉",
    "sage": "0",
    "admin": "0",
    "status": "n"
  },
  {
    "id": "30727504",
    "img": "",
    "ext": "",
    "now": "2020-09-27(日)06:55:12",
    "userid": "h1uKxl2",
    "name": "无名氏",
    "email": "",
    "title": "无标题",
    "content": "昨晚梦到陆生了，半梦半醒之间都喊着付意那种( ´_ゝ`)今天起来就看到肥哥们探讨了陆生･ﾟ( ﾉд`ﾟ)",
    "sage": "0",
    "admin": "0",
    "status": "n"
  },
  {
    "id": "30727555",
    "img": "",
    "ext": "",
    "now": "2020-09-27(日)07:03:35",
    "userid": "o72A6wF",
    "name": "无名氏",
    "email": "",
    "title": "无标题",
    "content": "( ﾟ∀。)2吧，真出铁丝倒是也说明这里不安全了",
    "sage": "0",
    "admin": "0",
    "status": "n"
  },
  {
    "id": "30734046",
    "img": "",
    "ext": "",
    "now": "2020-09-27(日)12:22:36",
    "userid": "wZvl6OW",
    "name": "无名氏",
    "email": "",
    "title": "无标题",
    "content": "<font color=\"#789922\">&gt;&gt;No.30727504</font><br />\n我也梦到过陆生在上个团刚结的时候，还梦到过韩老板一个背影･ﾟ( ﾉд`ﾟ)<br />\n2",
    "sage": "0",
    "admin": "0",
    "status": "n"
  },
  {
    "id": "30734618",
    "img": "",
    "ext": "",
    "now": "2020-09-27(日)12:41:35",
    "userid": "qoqDx7F",
    "name": "无名氏",
    "email": "",
    "title": "无标题",
    "content": "<font color=\"#789922\">&gt;&gt;No.30734046</font><br />\n是心电感应ﾟ(つд`ﾟ)",
    "sage": "0",
    "admin": "0",
    "status": "n"
  },
  {
    "id": "30734664",
    "img": "",
    "ext": "",
    "now": "2020-09-27(日)12:42:41",
    "userid": "qoqDx7F",
    "name": "无名氏",
    "email": "",
    "title": "无标题",
    "content": "还没投票，选2了看看有没有遗物",
    "sage": "0",
    "admin": "0",
    "status": "n"
  },
  {
    "id": "30737601",
    "img": "",
    "ext": "",
    "now": "2020-09-27(日)14:28:19",
    "userid": "fxc8mDE",
    "name": "无名氏",
    "email": "",
    "title": "无标题",
    "content": "2选项得票最多，剧情将按着这个发展ﾟ ∀ﾟ)ノ",
    "sage": "0",
    "admin": "0",
    "status": "n"
  },
  {
    "id": "30737607",
    "img": "",
    "ext": "",
    "now": "2020-09-27(日)14:28:48",
    "userid": "fxc8mDE",
    "name": "无名氏",
    "email": "",
    "title": "无标题",
    "content": "<font color=\"#789922\">&gt;&gt;No.30737601</font><br />\n<br />\n“好吧，希望是我多虑了。我们再查看下「他」的衣物内有没有遗物能证实「身份」的东西。”<br />\r\n说着你伸手在「垃圾」的西装里摸索着，上衣与裤兜里都空空如也。唯独在西装胸口处的内置口袋中摸出了一张全家福照片。<br />\r\n这是一张一眼就能看出是在小影楼里拍摄的全家福。<br />\r\n劣质的背景板加右下角富有年代感的时间编码：<br />\r\n「'10     2  13」<br />\r\n它拍摄于2010年2月13日。<br />\r\n2010年还有人用这种胶片机洗照片确实挺少见的。<br />\r\n照片里的「黑社会」大约三十七八模样，他和蔼的笑容与一身痞里痞气的装扮十分不和谐。旁边站着位差不多年纪的温和主妇，她笑起来与现在的温婉很像，像一朵永远盛开的丁香花。<br />\r\n他们双手搭在前面一个十三岁穿着红色棉袄笑容甜美的小女孩肩膀上——她是稚嫩的温婉。<br />\r\n照片的背面潦草的写着两行被蹭花的草书：<br />\r\n「传说是真的。」<br />\r\n「为了她们一切都值得。」<br />\r\n某人留下了这张全家福，使这具「垃圾」蒙上一层诡异的使命感的同时又像是在给自己害人的行径找了个恰当的借口——「我」并不是有意要「谋杀」你，而是不得不「牺牲」你。<br />\n\r<br />\n你_____<br />\n\r<br />\n1.没收这张全家福，让「垃圾」漂走<br />\r\n2.将全家福归还给「垃圾」后让「他」漂走",
    "sage": "0",
    "admin": "0",
    "status": "n"
  },
  {
    "id": "30737648",
    "img": "",
    "ext": "",
    "now": "2020-09-27(日)14:30:27",
    "userid": "fxc8mDE",
    "name": "无名氏",
    "email": "",
    "title": "无标题",
    "content": "请假请假，后天老时间更新(つд⊂)<br />\n今天赶画明天赶高铁(つд⊂)<br />\n肥哥们后天见(ゝ∀･)",
    "sage": "0",
    "admin": "0",
    "status": "n"
  },
  {
    "id": "30737827",
    "img": "",
    "ext": "",
    "now": "2020-09-27(日)14:38:49",
    "userid": "KwRQFWc",
    "name": "无名氏",
    "email": "",
    "title": "无标题",
    "content": "1吧，fxs辛苦了(ノﾟ∀ﾟ)ノ",
    "sage": "0",
    "admin": "0",
    "status": "n"
  },
  {
    "id": "30737869",
    "img": "",
    "ext": "",
    "now": "2020-09-27(日)14:41:00",
    "userid": "qoqDx7F",
    "name": "无名氏",
    "email": "",
    "title": "无标题",
    "content": "<font color=\"#789922\">&gt;&gt;No.30737648</font><br />\n辛苦啦(ノﾟ∀ﾟ)ノ",
    "sage": "0",
    "admin": "0",
    "status": "n"
  },
  {
    "id": "30738216",
    "img": "",
    "ext": "",
    "now": "2020-09-27(日)14:54:07",
    "userid": "h1uKxl2",
    "name": "无名氏",
    "email": "",
    "title": "无标题",
    "content": "<font color=\"#789922\">&gt;&gt;No.30737648</font><br />\n放心菜举高高(ノﾟ∀ﾟ)ノ",
    "sage": "0",
    "admin": "0",
    "status": "n"
  },
  {
    "id": "30738323",
    "img": "2020-09-27/5f7037e668126",
    "ext": ".png",
    "now": "2020-09-27(日)14:57:42",
    "userid": "qoqDx7F",
    "name": "无名氏",
    "email": "",
    "title": "无标题",
    "content": "山庄时间表更新，附图(・ー・)",
    "sage": "0",
    "admin": "0",
    "status": "n"
  },
  {
    "id": "30738341",
    "img": "",
    "ext": "",
    "now": "2020-09-27(日)14:58:50",
    "userid": "qoqDx7F",
    "name": "无名氏",
    "email": "",
    "title": "无标题",
    "content": "<font color=\"#789922\">&gt;&gt;No.30738323</font><br />\n温婉和酷哥一样大，比小鸟大一岁( ´_ゝ`)",
    "sage": "0",
    "admin": "0",
    "status": "n"
  },
  {
    "id": "30738525",
    "img": "",
    "ext": "",
    "now": "2020-09-27(日)15:06:37",
    "userid": "h7fpuoR",
    "name": "无名氏",
    "email": "",
    "title": "无标题",
    "content": "辛苦放心菜ﾟ ∀ﾟ)ノ",
    "sage": "0",
    "admin": "0",
    "status": "n"
  },
  {
    "id": "30739115",
    "img": "",
    "ext": "",
    "now": "2020-09-27(日)15:29:54",
    "userid": "wZvl6OW",
    "name": "无名氏",
    "email": "",
    "title": "无标题",
    "content": "<font color=\"#789922\">&gt;&gt;No.30738323</font><br />\n感谢肥哥整理(=ﾟωﾟ)=b",
    "sage": "0",
    "admin": "0",
    "status": "n"
  },
  {
    "id": "30739205",
    "img": "",
    "ext": "",
    "now": "2020-09-27(日)15:33:56",
    "userid": "wZvl6OW",
    "name": "无名氏",
    "email": "",
    "title": "无标题",
    "content": "<font color=\"#789922\">&gt;&gt;No.30737648</font><br />\n放心菜辛苦(ノﾟ∀ﾟ)ノ<br />\n转眼十一要到了，从月下团一路过了这么久，每天都有放心菜的陪伴(=ﾟωﾟ)=",
    "sage": "0",
    "admin": "0",
    "status": "n"
  },
  {
    "id": "30741646",
    "img": "",
    "ext": "",
    "now": "2020-09-27(日)17:07:34",
    "userid": "OedwoD8",
    "name": "无名氏",
    "email": "",
    "title": "无标题",
    "content": "<font color=\"#789922\">&gt;&gt;No.30737607</font><br />\n2，但用手机拍一下照片和尸体的照片ᕕ( ᐛ )ᕗ",
    "sage": "0",
    "admin": "0",
    "status": "n"
  },
  {
    "id": "30742817",
    "img": "",
    "ext": "",
    "now": "2020-09-27(日)17:45:59",
    "userid": "DejC1TS",
    "name": "无名氏",
    "email": "",
    "title": "无标题",
    "content": "<font color=\"#789922\">&gt;&gt;No.30741646</font><br />\n附议(＾o＾)ﾉ",
    "sage": "0",
    "admin": "0",
    "status": "n"
  }
]