[
  {
    "id": "31249427",
    "img": "",
    "ext": "",
    "now": "2020-10-15(四)21:12:30",
    "userid": "Ec6tzay",
    "name": "无名氏",
    "email": "",
    "title": "无标题",
    "content": "<font color=\"#789922\">&gt;&gt;No.31248665</font><br />\n你这个试探方法我觉得说不定真能试出些什么，但是 突然说这句话很奇怪啊",
    "sage": "0",
    "admin": "0",
    "status": "n"
  },
  {
    "id": "31249650",
    "img": "",
    "ext": "",
    "now": "2020-10-15(四)21:22:20",
    "userid": "qoqDx7F",
    "name": "无名氏",
    "email": "",
    "title": "无标题",
    "content": "<font color=\"#789922\">&gt;&gt;No.31249427</font><br />\n那润色一下……？( ﾟ∀。)<br />\n小花，其实你也明白的吧……你不承认只是想再见到她，但是她说不定其实就在你身边守望着你，把那堆亵渎死者的造物当成她，她又会怎么想呢( ´_ゝ`)",
    "sage": "0",
    "admin": "0",
    "status": "n"
  },
  {
    "id": "31249701",
    "img": "",
    "ext": "",
    "now": "2020-10-15(四)21:24:42",
    "userid": "qoqDx7F",
    "name": "无名氏",
    "email": "",
    "title": "无标题",
    "content": "<font color=\"#789922\">&gt;&gt;No.31249650</font><br />\n然后找个合适的时机吟诗？( ﾟ∀。)",
    "sage": "0",
    "admin": "0",
    "status": "n"
  },
  {
    "id": "31249823",
    "img": "",
    "ext": "",
    "now": "2020-10-15(四)21:28:48",
    "userid": "Ec6tzay",
    "name": "无名氏",
    "email": "",
    "title": "无标题",
    "content": "说实话等会谁来搬运小花是个问题(｀・ω)都不一定能顾及他们了 我们能把我们自己和老板保护好就已经是圆满完成任务了",
    "sage": "0",
    "admin": "0",
    "status": "n"
  },
  {
    "id": "31250482",
    "img": "",
    "ext": "",
    "now": "2020-10-15(四)21:56:55",
    "userid": "fxc8mDE",
    "name": "无名氏",
    "email": "",
    "title": "无标题",
    "content": "2选项得票最多，融合了前面肥哥们自定义的对话，剧情将按着这个发展ﾟ ∀ﾟ)ノ",
    "sage": "0",
    "admin": "0",
    "status": "n"
  },
  {
    "id": "31250531",
    "img": "",
    "ext": "",
    "now": "2020-10-15(四)21:58:51",
    "userid": "fxc8mDE",
    "name": "无名氏",
    "email": "",
    "title": "无标题",
    "content": "<font color=\"#789922\">&gt;&gt;No.31250482</font><br />\n<br />\n“万越……”你轻声呼喊着万越，他会意的向翁语涵身侧走去。<br />\r\n没有意识到即将要发生什么的翁语涵自顾自的说着些你们无法理解的胡话，你们带着怜悯而又果决的目光看着她——翁语涵或许是无法接受闫欣的死亡，或许是无法承受王明的牺牲，她自我拉扯着逃避这荒谬的现实。<br />\r\n“语涵，其实你也明白的吧……你不承认只是想再见到她，但是她说不定其实就在你身边守望着你。把那堆亵渎死者的造物当成她，她又会怎么想呢？就像你之前所说「就让我们一起坠落到地狱深处吧，和比翼飞上天堂，也没什么两样。」”<br />\r\n“认清现实吧，你早就知道的，她已经死了。现在我们要解决「怪奇」，所以，语涵你好好休息休息，我们会保护你。”<br />\r\n你口头上安慰着精神不稳定的翁语涵，她复述着那句闫欣曾经读给她的诗，全不顾及形象的痛哭流涕。<br />\r\n你冲她身侧的万越点点头，他熟练的将翁语涵击晕。以防万一，你抽出绳子将翁语涵的手脚绑住。自身难保的温婉与老吴在确认了翁语涵的精神状态后也没有在这些细枝末节之上多过纠结。<br />\r\n你用手背擦拭着额头上的汗水，本应该刮着清凉夜风的夏末天台上不知何时变得有些闷热。<br />\r\n今夜会下雨吗？<br />\r\n一轮弦月毫无阴云遮掩的挂在天边。<br />\r\n诡异的闷热挤压着你裸露在外的喉咙，你深吸了几口气试图缓解心中莫名的窒息感。<br />\r\n咚咚咚——<br />\r\n急促的敲门声从天台门后传来。<br />\r\n所有人都如遭雷击般，重重的打了一个哆嗦望向那扇老旧的天台门。<br />\r\n“你们在吗？是我，闫欣。”<br />\r\n属于闫欣特有的低哑女声从门后传来。<br />\r\n你有些庆幸你们及时击晕了翁语涵，要不事情很有可能会朝着意想不到的方向发展。<br />\n\r<br />\n你_____<br />\n\r<br />\n1.应门<br />\r\n2.不说话",
    "sage": "0",
    "admin": "0",
    "status": "n"
  },
  {
    "id": "31250627",
    "img": "",
    "ext": "",
    "now": "2020-10-15(四)22:02:32",
    "userid": "5oZzmv3",
    "name": "无名氏",
    "email": "",
    "title": "无标题",
    "content": "正片要开始了么(((　ﾟдﾟ)))",
    "sage": "0",
    "admin": "0",
    "status": "n"
  },
  {
    "id": "31250695",
    "img": "",
    "ext": "",
    "now": "2020-10-15(四)22:05:25",
    "userid": "o72A6wF",
    "name": "无名氏",
    "email": "",
    "title": "无标题",
    "content": "(*ﾟーﾟ)不过闫欣那个尸体确实我记得是没有脸的吧？<br />\n2稳一点",
    "sage": "0",
    "admin": "0",
    "status": "n"
  },
  {
    "id": "31250698",
    "img": "",
    "ext": "",
    "now": "2020-10-15(四)22:05:40",
    "userid": "Ec6tzay",
    "name": "无名氏",
    "email": "",
    "title": "无标题",
    "content": "不说话( ﾟ∀。)",
    "sage": "0",
    "admin": "0",
    "status": "n"
  },
  {
    "id": "31250792",
    "img": "",
    "ext": "",
    "now": "2020-10-15(四)22:09:32",
    "userid": "FToovvr",
    "name": "无名氏",
    "email": "",
    "title": "无标题",
    "content": "之后有对话环节记得不要喊名字，说不定这里来的其实是「打生桩」怪谈(*ﾟーﾟ)",
    "sage": "0",
    "admin": "0",
    "status": "n"
  },
  {
    "id": "31250819",
    "img": "",
    "ext": "",
    "now": "2020-10-15(四)22:10:30",
    "userid": "Ec6tzay",
    "name": "无名氏",
    "email": "",
    "title": "无标题",
    "content": "出现了 fto兄( ﾟ∀。)",
    "sage": "0",
    "admin": "0",
    "status": "n"
  },
  {
    "id": "31250844",
    "img": "",
    "ext": "",
    "now": "2020-10-15(四)22:11:33",
    "userid": "h1uKxl2",
    "name": "无名氏",
    "email": "",
    "title": "无标题",
    "content": "fto兄终于来了(*´∀`)",
    "sage": "0",
    "admin": "0",
    "status": "n"
  },
  {
    "id": "31250901",
    "img": "",
    "ext": "",
    "now": "2020-10-15(四)22:14:22",
    "userid": "FToovvr",
    "name": "无名氏",
    "email": "",
    "title": "无标题",
    "content": "( ﾟ∀。)最近事情比较多",
    "sage": "0",
    "admin": "0",
    "status": "n"
  },
  {
    "id": "31251075",
    "img": "",
    "ext": "",
    "now": "2020-10-15(四)22:20:45",
    "userid": "DejC1TS",
    "name": "无名氏",
    "email": "",
    "title": "无标题",
    "content": "是fto兄(=ﾟωﾟ)=",
    "sage": "0",
    "admin": "0",
    "status": "n"
  },
  {
    "id": "31251109",
    "img": "",
    "ext": "",
    "now": "2020-10-15(四)22:21:50",
    "userid": "DejC1TS",
    "name": "无名氏",
    "email": "",
    "title": "无标题",
    "content": "2比较稳妥我2",
    "sage": "0",
    "admin": "0",
    "status": "n"
  },
  {
    "id": "31251509",
    "img": "",
    "ext": "",
    "now": "2020-10-15(四)22:36:55",
    "userid": "qoqDx7F",
    "name": "无名氏",
    "email": "",
    "title": "无标题",
    "content": "FTo兄来了(*ﾟ∇ﾟ)",
    "sage": "0",
    "admin": "0",
    "status": "n"
  },
  {
    "id": "31251519",
    "img": "",
    "ext": "",
    "now": "2020-10-15(四)22:37:12",
    "userid": "qoqDx7F",
    "name": "无名氏",
    "email": "",
    "title": "无标题",
    "content": "2",
    "sage": "0",
    "admin": "0",
    "status": "n"
  },
  {
    "id": "31251553",
    "img": "",
    "ext": "",
    "now": "2020-10-15(四)22:38:31",
    "userid": "RQAfqcy",
    "name": "无名氏",
    "email": "",
    "title": "无标题",
    "content": "2",
    "sage": "0",
    "admin": "0",
    "status": "n"
  },
  {
    "id": "31251829",
    "img": "",
    "ext": "",
    "now": "2020-10-15(四)22:49:54",
    "userid": "wZvl6OW",
    "name": "无名氏",
    "email": "",
    "title": "无标题",
    "content": "2",
    "sage": "0",
    "admin": "0",
    "status": "n"
  }
]